{
  "type": "object",
  "strict": true,
  "properties": {
    "status": {
      "type": "string",
      "enum": [
        "success",
        "error",
        "partial"
      ],
      "description": "Processing status of the request (success, error, or partial completion)"
    },
    "errors": {
      "type": "array",
      "items": {
        "type": "object",
        "properties": {
          "code": {
            "type": "string",
            "description": "Error code identifier for programmatic handling"
          },
          "message": {
            "type": "string",
            "description": "Human-readable error description"
          },
          "field": {
            "type": "string",
            "description": "Specific field that triggered the error"
          },
          "severity": {
            "type": "string",
            "enum": [
              "error",
              "warning"
            ],
            "description": "Error severity level (critical error or advisory warning)"
          }
        },
        "required": [
          "code",
          "message",
          "field",
          "severity"
        ]
      },
      "nullable": true,
      "description": "List of errors encountered during processing, null if no errors"
    },
    "data": {
      "type": "object",
      "properties": {
        "company": {
          "type": "string",
          "description": "Full legal company name without suffixes (unless part of common name)"
        },
        "start": {
          "type": "string",
          "nullable": true,
          "description": "Overall employment start date in 'MMM YYYY' format (or YYYY if only year mentioned)"
        },
        "end": {
          "type": "string",
          "nullable": true,
          "description": "Overall employment end date in 'MMM YYYY' format (null if current position)"
        },
        "current": {
          "type": "boolean",
          "description": "Indicates if this is a current position (true) or past position (false)"
        },
        "summary": {
          "type": "string",
          "nullable": true,
          "description": "Concise overview of responsibilities (max 400 chars) relevant to target role"
        },
        "highlights": {
          "type": "array",
          "items": {
            "type": "string"
          },
          "nullable": true,
          "description": "Key achievements (max 6, 200 chars each) with measurable impact and STAR format"
        },
        "roles": {
          "type": "array",
          "items": {
            "type": "object",
            "properties": {
              "title": {
                "type": "string",
                "description": "Exact job title with standardized abbreviations"
              },
              "start": {
                "type": "string",
                "nullable": true,
                "description": "Role-specific start date in 'MMM YYYY' format (or YYYY if only year mentioned)"
              },
              "end": {
                "type": "string",
                "nullable": true,
                "description": "Role-specific end date in 'MMM YYYY' format (null if current role)"
              },
              "current": {
                "type": "boolean",
                "nullable": true,
                "description": "Indicates if this specific role is current (true) or past (false)"
              }
            },
            "required": [
              "title",
              "start",
              "end",
              "current"
            ]
          },
          "description": "All positions held at this company with individual dates"
        },
        "feedback": {
          "type": "object",
          "properties": {
            "strengths": {
              "type": "array",
              "items": {
                "type": "string"
              },
              "description": "Effective aspects of the role description"
            },
            "areas_to_improve": {
              "type": "array",
              "items": {
                "type": "string"
              },
              "description": "Suggestions to enhance role relevance to target position"
            }
          },
          "required": [
            "strengths",
            "areas_to_improve"
          ],
          "description": "Evaluation of role description quality and alignment with target position"
        }
      },
      "required": [
        "company",
        "roles",
        "start",
        "end",
        "current",
        "summary",
        "highlights",
        "feedback"
      ],
      "description": "Container for optimized work experience and evaluation feedback"
    }
  },
  "required": [
    "status",
    "errors",
    "data"
  ]
}